{
  "sprinkler_count": "5",
  "devices_per_sprinkler": "5",
  "latitude": "10",
  "longitude": "10",
  "min_percentage_to_alarm": "40",
  "sprinkler1": ["soil_temp_sensor_device_11", "soil_mois_sensor_device_11",
    "soil_temp_sensor_device_12", "soil_mois_sensor_device_12",
    "soil_temp_sensor_device_13", "soil_mois_sensor_device_13",
    "soil_temp_sensor_device_14", "soil_mois_sensor_device_14",
    "soil_temp_sensor_device_15", "soil_mois_sensor_device_15"
  ],
  "sprinkler2": ["soil_temp_sensor_device_21", "soil_mois_sensor_device_21",
    "soil_temp_sensor_device_22", "soil_mois_sensor_device_22",
    "soil_temp_sensor_device_23", "soil_mois_sensor_device_23",
    "soil_temp_sensor_device_24", "soil_mois_sensor_device_24",
    "soil_temp_sensor_device_25", "soil_mois_sensor_device_25"
  ]
}